{
  "type": "File",
  "start": 0,
  "end": 612,
  "loc": {
    "start": {
      "line": 1,
      "column": 0
    },
    "end": {
      "line": 24,
      "column": 0
    }
  },
  "program": {
    "type": "Program",
    "start": 0,
    "end": 612,
    "loc": {
      "start": {
        "line": 1,
        "column": 0
      },
      "end": {
        "line": 24,
        "column": 0
      }
    },
    "sourceType": "module",
    "body": [
      {
        "type": "ImportDeclaration",
        "start": 0,
        "end": 57,
        "loc": {
          "start": {
            "line": 1,
            "column": 0
          },
          "end": {
            "line": 1,
            "column": 57
          }
        },
        "specifiers": [
          {
            "type": "ImportDefaultSpecifier",
            "start": 7,
            "end": 25,
            "loc": {
              "start": {
                "line": 1,
                "column": 7
              },
              "end": {
                "line": 1,
                "column": 25
              }
            },
            "local": {
              "type": "Identifier",
              "start": 7,
              "end": 25,
              "loc": {
                "start": {
                  "line": 1,
                  "column": 7
                },
                "end": {
                  "line": 1,
                  "column": 25
                },
                "identifierName": "validateLineLength"
              },
              "name": "validateLineLength"
            }
          }
        ],
        "source": {
          "type": "StringLiteral",
          "start": 31,
          "end": 56,
          "loc": {
            "start": {
              "line": 1,
              "column": 31
            },
            "end": {
              "line": 1,
              "column": 56
            }
          },
          "extra": {
            "rawValue": "./validateLineLength.js",
            "raw": "'./validateLineLength.js'"
          },
          "value": "./validateLineLength.js"
        }
      },
      {
        "type": "ImportDeclaration",
        "start": 58,
        "end": 121,
        "loc": {
          "start": {
            "line": 2,
            "column": 0
          },
          "end": {
            "line": 2,
            "column": 63
          }
        },
        "specifiers": [
          {
            "type": "ImportDefaultSpecifier",
            "start": 65,
            "end": 86,
            "loc": {
              "start": {
                "line": 2,
                "column": 7
              },
              "end": {
                "line": 2,
                "column": 28
              }
            },
            "local": {
              "type": "Identifier",
              "start": 65,
              "end": 86,
              "loc": {
                "start": {
                  "line": 2,
                  "column": 7
                },
                "end": {
                  "line": 2,
                  "column": 28
                },
                "identifierName": "validateRequiredField"
              },
              "name": "validateRequiredField"
            }
          }
        ],
        "source": {
          "type": "StringLiteral",
          "start": 92,
          "end": 120,
          "loc": {
            "start": {
              "line": 2,
              "column": 34
            },
            "end": {
              "line": 2,
              "column": 62
            }
          },
          "extra": {
            "rawValue": "./validateRequiredField.js",
            "raw": "'./validateRequiredField.js'"
          },
          "value": "./validateRequiredField.js"
        }
      },
      {
        "type": "ImportDeclaration",
        "start": 123,
        "end": 170,
        "loc": {
          "start": {
            "line": 4,
            "column": 0
          },
          "end": {
            "line": 4,
            "column": 47
          }
        },
        "specifiers": [
          {
            "type": "ImportDefaultSpecifier",
            "start": 130,
            "end": 143,
            "loc": {
              "start": {
                "line": 4,
                "column": 7
              },
              "end": {
                "line": 4,
                "column": 20
              }
            },
            "local": {
              "type": "Identifier",
              "start": 130,
              "end": 143,
              "loc": {
                "start": {
                  "line": 4,
                  "column": 7
                },
                "end": {
                  "line": 4,
                  "column": 20
                },
                "identifierName": "parseDateTime"
              },
              "name": "parseDateTime"
            }
          }
        ],
        "source": {
          "type": "StringLiteral",
          "start": 149,
          "end": 169,
          "loc": {
            "start": {
              "line": 4,
              "column": 26
            },
            "end": {
              "line": 4,
              "column": 46
            }
          },
          "extra": {
            "rawValue": "./parseDateTime.js",
            "raw": "'./parseDateTime.js'"
          },
          "value": "./parseDateTime.js"
        }
      },
      {
        "type": "ImportDeclaration",
        "start": 171,
        "end": 214,
        "loc": {
          "start": {
            "line": 5,
            "column": 0
          },
          "end": {
            "line": 5,
            "column": 43
          }
        },
        "specifiers": [
          {
            "type": "ImportDefaultSpecifier",
            "start": 178,
            "end": 189,
            "loc": {
              "start": {
                "line": 5,
                "column": 7
              },
              "end": {
                "line": 5,
                "column": 18
              }
            },
            "local": {
              "type": "Identifier",
              "start": 178,
              "end": 189,
              "loc": {
                "start": {
                  "line": 5,
                  "column": 7
                },
                "end": {
                  "line": 5,
                  "column": 18
                },
                "identifierName": "parseStatus"
              },
              "name": "parseStatus"
            }
          }
        ],
        "source": {
          "type": "StringLiteral",
          "start": 195,
          "end": 213,
          "loc": {
            "start": {
              "line": 5,
              "column": 24
            },
            "end": {
              "line": 5,
              "column": 42
            }
          },
          "extra": {
            "rawValue": "./parseStatus.js",
            "raw": "'./parseStatus.js'"
          },
          "value": "./parseStatus.js"
        }
      },
      {
        "type": "ExportDefaultDeclaration",
        "start": 216,
        "end": 611,
        "loc": {
          "start": {
            "line": 7,
            "column": 0
          },
          "end": {
            "line": 23,
            "column": 1
          }
        },
        "declaration": {
          "type": "FunctionDeclaration",
          "start": 231,
          "end": 611,
          "loc": {
            "start": {
              "line": 7,
              "column": 15
            },
            "end": {
              "line": 23,
              "column": 1
            }
          },
          "id": {
            "type": "Identifier",
            "start": 240,
            "end": 247,
            "loc": {
              "start": {
                "line": 7,
                "column": 24
              },
              "end": {
                "line": 7,
                "column": 31
              },
              "identifierName": "parseA4"
            },
            "name": "parseA4"
          },
          "generator": false,
          "expression": false,
          "async": false,
          "params": [
            {
              "type": "Identifier",
              "start": 248,
              "end": 253,
              "loc": {
                "start": {
                  "line": 7,
                  "column": 32
                },
                "end": {
                  "line": 7,
                  "column": 37
                },
                "identifierName": "parts"
              },
              "name": "parts"
            },
            {
              "type": "Identifier",
              "start": 255,
              "end": 262,
              "loc": {
                "start": {
                  "line": 7,
                  "column": 39
                },
                "end": {
                  "line": 7,
                  "column": 46
                },
                "identifierName": "options"
              },
              "name": "options"
            }
          ],
          "body": {
            "type": "BlockStatement",
            "start": 264,
            "end": 611,
            "loc": {
              "start": {
                "line": 7,
                "column": 48
              },
              "end": {
                "line": 23,
                "column": 1
              }
            },
            "body": [
              {
                "type": "ExpressionStatement",
                "start": 267,
                "end": 323,
                "loc": {
                  "start": {
                    "line": 8,
                    "column": 1
                  },
                  "end": {
                    "line": 8,
                    "column": 57
                  }
                },
                "expression": {
                  "type": "CallExpression",
                  "start": 267,
                  "end": 322,
                  "loc": {
                    "start": {
                      "line": 8,
                      "column": 1
                    },
                    "end": {
                      "line": 8,
                      "column": 56
                    }
                  },
                  "callee": {
                    "type": "Identifier",
                    "start": 267,
                    "end": 285,
                    "loc": {
                      "start": {
                        "line": 8,
                        "column": 1
                      },
                      "end": {
                        "line": 8,
                        "column": 19
                      },
                      "identifierName": "validateLineLength"
                    },
                    "name": "validateLineLength"
                  },
                  "arguments": [
                    {
                      "type": "Identifier",
                      "start": 286,
                      "end": 291,
                      "loc": {
                        "start": {
                          "line": 8,
                          "column": 20
                        },
                        "end": {
                          "line": 8,
                          "column": 25
                        },
                        "identifierName": "parts"
                      },
                      "name": "parts"
                    },
                    {
                      "type": "StringLiteral",
                      "start": 293,
                      "end": 297,
                      "loc": {
                        "start": {
                          "line": 8,
                          "column": 27
                        },
                        "end": {
                          "line": 8,
                          "column": 31
                        }
                      },
                      "extra": {
                        "rawValue": "A4",
                        "raw": "'A4'"
                      },
                      "value": "A4"
                    },
                    {
                      "type": "NumericLiteral",
                      "start": 299,
                      "end": 300,
                      "loc": {
                        "start": {
                          "line": 8,
                          "column": 33
                        },
                        "end": {
                          "line": 8,
                          "column": 34
                        }
                      },
                      "extra": {
                        "rawValue": 6,
                        "raw": "6"
                      },
                      "value": 6
                    },
                    {
                      "type": "MemberExpression",
                      "start": 302,
                      "end": 321,
                      "loc": {
                        "start": {
                          "line": 8,
                          "column": 36
                        },
                        "end": {
                          "line": 8,
                          "column": 55
                        }
                      },
                      "object": {
                        "type": "MemberExpression",
                        "start": 302,
                        "end": 318,
                        "loc": {
                          "start": {
                            "line": 8,
                            "column": 36
                          },
                          "end": {
                            "line": 8,
                            "column": 52
                          }
                        },
                        "object": {
                          "type": "Identifier",
                          "start": 302,
                          "end": 309,
                          "loc": {
                            "start": {
                              "line": 8,
                              "column": 36
                            },
                            "end": {
                              "line": 8,
                              "column": 43
                            },
                            "identifierName": "options"
                          },
                          "name": "options"
                        },
                        "property": {
                          "type": "Identifier",
                          "start": 310,
                          "end": 318,
                          "loc": {
                            "start": {
                              "line": 8,
                              "column": 44
                            },
                            "end": {
                              "line": 8,
                              "column": 52
                            },
                            "identifierName": "trailing"
                          },
                          "name": "trailing"
                        },
                        "computed": false
                      },
                      "property": {
                        "type": "Identifier",
                        "start": 319,
                        "end": 321,
                        "loc": {
                          "start": {
                            "line": 8,
                            "column": 53
                          },
                          "end": {
                            "line": 8,
                            "column": 55
                          },
                          "identifierName": "A4"
                        },
                        "name": "A4"
                      },
                      "computed": false
                    }
                  ]
                }
              },
              {
                "type": "ExpressionStatement",
                "start": 325,
                "end": 365,
                "loc": {
                  "start": {
                    "line": 9,
                    "column": 1
                  },
                  "end": {
                    "line": 9,
                    "column": 41
                  }
                },
                "expression": {
                  "type": "CallExpression",
                  "start": 325,
                  "end": 364,
                  "loc": {
                    "start": {
                      "line": 9,
                      "column": 1
                    },
                    "end": {
                      "line": 9,
                      "column": 40
                    }
                  },
                  "callee": {
                    "type": "Identifier",
                    "start": 325,
                    "end": 346,
                    "loc": {
                      "start": {
                        "line": 9,
                        "column": 1
                      },
                      "end": {
                        "line": 9,
                        "column": 22
                      },
                      "identifierName": "validateRequiredField"
                    },
                    "name": "validateRequiredField"
                  },
                  "arguments": [
                    {
                      "type": "Identifier",
                      "start": 347,
                      "end": 352,
                      "loc": {
                        "start": {
                          "line": 9,
                          "column": 23
                        },
                        "end": {
                          "line": 9,
                          "column": 28
                        },
                        "identifierName": "parts"
                      },
                      "name": "parts"
                    },
                    {
                      "type": "StringLiteral",
                      "start": 354,
                      "end": 360,
                      "loc": {
                        "start": {
                          "line": 9,
                          "column": 30
                        },
                        "end": {
                          "line": 9,
                          "column": 36
                        }
                      },
                      "extra": {
                        "rawValue": "date",
                        "raw": "'date'"
                      },
                      "value": "date"
                    },
                    {
                      "type": "NumericLiteral",
                      "start": 362,
                      "end": 363,
                      "loc": {
                        "start": {
                          "line": 9,
                          "column": 38
                        },
                        "end": {
                          "line": 9,
                          "column": 39
                        }
                      },
                      "extra": {
                        "rawValue": 4,
                        "raw": "4"
                      },
                      "value": 4
                    }
                  ]
                }
              },
              {
                "type": "VariableDeclaration",
                "start": 368,
                "end": 443,
                "loc": {
                  "start": {
                    "line": 11,
                    "column": 1
                  },
                  "end": {
                    "line": 11,
                    "column": 76
                  }
                },
                "declarations": [
                  {
                    "type": "VariableDeclarator",
                    "start": 374,
                    "end": 442,
                    "loc": {
                      "start": {
                        "line": 11,
                        "column": 7
                      },
                      "end": {
                        "line": 11,
                        "column": 75
                      }
                    },
                    "id": {
                      "type": "ArrayPattern",
                      "start": 374,
                      "end": 434,
                      "loc": {
                        "start": {
                          "line": 11,
                          "column": 7
                        },
                        "end": {
                          "line": 11,
                          "column": 67
                        }
                      },
                      "elements": [
                        {
                          "type": "Identifier",
                          "start": 375,
                          "end": 385,
                          "loc": {
                            "start": {
                              "line": 11,
                              "column": 8
                            },
                            "end": {
                              "line": 11,
                              "column": 18
                            },
                            "identifierName": "descriptor"
                          },
                          "name": "descriptor"
                        },
                        {
                          "type": "Identifier",
                          "start": 387,
                          "end": 396,
                          "loc": {
                            "start": {
                              "line": 11,
                              "column": 20
                            },
                            "end": {
                              "line": 11,
                              "column": 29
                            },
                            "identifierName": "reference"
                          },
                          "name": "reference"
                        },
                        {
                          "type": "Identifier",
                          "start": 398,
                          "end": 407,
                          "loc": {
                            "start": {
                              "line": 11,
                              "column": 31
                            },
                            "end": {
                              "line": 11,
                              "column": 40
                            },
                            "identifierName": "requestor"
                          },
                          "name": "requestor"
                        },
                        {
                          "type": "Identifier",
                          "start": 409,
                          "end": 413,
                          "loc": {
                            "start": {
                              "line": 11,
                              "column": 42
                            },
                            "end": {
                              "line": 11,
                              "column": 46
                            },
                            "identifierName": "date"
                          },
                          "name": "date"
                        },
                        {
                          "type": "Identifier",
                          "start": 415,
                          "end": 419,
                          "loc": {
                            "start": {
                              "line": 11,
                              "column": 48
                            },
                            "end": {
                              "line": 11,
                              "column": 52
                            },
                            "identifierName": "time"
                          },
                          "name": "time"
                        },
                        {
                          "type": "Identifier",
                          "start": 421,
                          "end": 433,
                          "loc": {
                            "start": {
                              "line": 11,
                              "column": 54
                            },
                            "end": {
                              "line": 11,
                              "column": 66
                            },
                            "identifierName": "statusString"
                          },
                          "name": "statusString"
                        }
                      ]
                    },
                    "init": {
                      "type": "Identifier",
                      "start": 437,
                      "end": 442,
                      "loc": {
                        "start": {
                          "line": 11,
                          "column": 70
                        },
                        "end": {
                          "line": 11,
                          "column": 75
                        },
                        "identifierName": "parts"
                      },
                      "name": "parts"
                    }
                  }
                ],
                "kind": "const"
              },
              {
                "type": "VariableDeclaration",
                "start": 446,
                "end": 489,
                "loc": {
                  "start": {
                    "line": 13,
                    "column": 1
                  },
                  "end": {
                    "line": 13,
                    "column": 44
                  }
                },
                "declarations": [
                  {
                    "type": "VariableDeclarator",
                    "start": 452,
                    "end": 488,
                    "loc": {
                      "start": {
                        "line": 13,
                        "column": 7
                      },
                      "end": {
                        "line": 13,
                        "column": 43
                      }
                    },
                    "id": {
                      "type": "Identifier",
                      "start": 452,
                      "end": 460,
                      "loc": {
                        "start": {
                          "line": 13,
                          "column": 7
                        },
                        "end": {
                          "line": 13,
                          "column": 15
                        },
                        "identifierName": "datetime"
                      },
                      "name": "datetime"
                    },
                    "init": {
                      "type": "CallExpression",
                      "start": 463,
                      "end": 488,
                      "loc": {
                        "start": {
                          "line": 13,
                          "column": 18
                        },
                        "end": {
                          "line": 13,
                          "column": 43
                        }
                      },
                      "callee": {
                        "type": "Identifier",
                        "start": 463,
                        "end": 476,
                        "loc": {
                          "start": {
                            "line": 13,
                            "column": 18
                          },
                          "end": {
                            "line": 13,
                            "column": 31
                          },
                          "identifierName": "parseDateTime"
                        },
                        "name": "parseDateTime"
                      },
                      "arguments": [
                        {
                          "type": "Identifier",
                          "start": 477,
                          "end": 481,
                          "loc": {
                            "start": {
                              "line": 13,
                              "column": 32
                            },
                            "end": {
                              "line": 13,
                              "column": 36
                            },
                            "identifierName": "date"
                          },
                          "name": "date"
                        },
                        {
                          "type": "Identifier",
                          "start": 483,
                          "end": 487,
                          "loc": {
                            "start": {
                              "line": 13,
                              "column": 38
                            },
                            "end": {
                              "line": 13,
                              "column": 42
                            },
                            "identifierName": "time"
                          },
                          "name": "time"
                        }
                      ]
                    }
                  }
                ],
                "kind": "const"
              },
              {
                "type": "VariableDeclaration",
                "start": 491,
                "end": 532,
                "loc": {
                  "start": {
                    "line": 14,
                    "column": 1
                  },
                  "end": {
                    "line": 14,
                    "column": 42
                  }
                },
                "declarations": [
                  {
                    "type": "VariableDeclarator",
                    "start": 497,
                    "end": 531,
                    "loc": {
                      "start": {
                        "line": 14,
                        "column": 7
                      },
                      "end": {
                        "line": 14,
                        "column": 41
                      }
                    },
                    "id": {
                      "type": "Identifier",
                      "start": 497,
                      "end": 503,
                      "loc": {
                        "start": {
                          "line": 14,
                          "column": 7
                        },
                        "end": {
                          "line": 14,
                          "column": 13
                        },
                        "identifierName": "status"
                      },
                      "name": "status"
                    },
                    "init": {
                      "type": "CallExpression",
                      "start": 506,
                      "end": 531,
                      "loc": {
                        "start": {
                          "line": 14,
                          "column": 16
                        },
                        "end": {
                          "line": 14,
                          "column": 41
                        }
                      },
                      "callee": {
                        "type": "Identifier",
                        "start": 506,
                        "end": 517,
                        "loc": {
                          "start": {
                            "line": 14,
                            "column": 16
                          },
                          "end": {
                            "line": 14,
                            "column": 27
                          },
                          "identifierName": "parseStatus"
                        },
                        "name": "parseStatus"
                      },
                      "arguments": [
                        {
                          "type": "Identifier",
                          "start": 518,
                          "end": 530,
                          "loc": {
                            "start": {
                              "line": 14,
                              "column": 28
                            },
                            "end": {
                              "line": 14,
                              "column": 40
                            },
                            "identifierName": "statusString"
                          },
                          "name": "statusString"
                        }
                      ]
                    }
                  }
                ],
                "kind": "const"
              },
              {
                "type": "ReturnStatement",
                "start": 535,
                "end": 609,
                "loc": {
                  "start": {
                    "line": 16,
                    "column": 1
                  },
                  "end": {
                    "line": 22,
                    "column": 3
                  }
                },
                "argument": {
                  "type": "ObjectExpression",
                  "start": 542,
                  "end": 608,
                  "loc": {
                    "start": {
                      "line": 16,
                      "column": 8
                    },
                    "end": {
                      "line": 22,
                      "column": 2
                    }
                  },
                  "properties": [
                    {
                      "type": "ObjectProperty",
                      "start": 546,
                      "end": 556,
                      "loc": {
                        "start": {
                          "line": 17,
                          "column": 2
                        },
                        "end": {
                          "line": 17,
                          "column": 12
                        }
                      },
                      "method": false,
                      "shorthand": true,
                      "computed": false,
                      "key": {
                        "type": "Identifier",
                        "start": 546,
                        "end": 556,
                        "loc": {
                          "start": {
                            "line": 17,
                            "column": 2
                          },
                          "end": {
                            "line": 17,
                            "column": 12
                          },
                          "identifierName": "descriptor"
                        },
                        "name": "descriptor"
                      },
                      "value": {
                        "type": "Identifier",
                        "start": 546,
                        "end": 556,
                        "loc": {
                          "start": {
                            "line": 17,
                            "column": 2
                          },
                          "end": {
                            "line": 17,
                            "column": 12
                          },
                          "identifierName": "descriptor"
                        },
                        "name": "descriptor"
                      },
                      "extra": {
                        "shorthand": true
                      }
                    },
                    {
                      "type": "ObjectProperty",
                      "start": 560,
                      "end": 569,
                      "loc": {
                        "start": {
                          "line": 18,
                          "column": 2
                        },
                        "end": {
                          "line": 18,
                          "column": 11
                        }
                      },
                      "method": false,
                      "shorthand": true,
                      "computed": false,
                      "key": {
                        "type": "Identifier",
                        "start": 560,
                        "end": 569,
                        "loc": {
                          "start": {
                            "line": 18,
                            "column": 2
                          },
                          "end": {
                            "line": 18,
                            "column": 11
                          },
                          "identifierName": "reference"
                        },
                        "name": "reference"
                      },
                      "value": {
                        "type": "Identifier",
                        "start": 560,
                        "end": 569,
                        "loc": {
                          "start": {
                            "line": 18,
                            "column": 2
                          },
                          "end": {
                            "line": 18,
                            "column": 11
                          },
                          "identifierName": "reference"
                        },
                        "name": "reference"
                      },
                      "extra": {
                        "shorthand": true
                      }
                    },
                    {
                      "type": "ObjectProperty",
                      "start": 573,
                      "end": 582,
                      "loc": {
                        "start": {
                          "line": 19,
                          "column": 2
                        },
                        "end": {
                          "line": 19,
                          "column": 11
                        }
                      },
                      "method": false,
                      "shorthand": true,
                      "computed": false,
                      "key": {
                        "type": "Identifier",
                        "start": 573,
                        "end": 582,
                        "loc": {
                          "start": {
                            "line": 19,
                            "column": 2
                          },
                          "end": {
                            "line": 19,
                            "column": 11
                          },
                          "identifierName": "requestor"
                        },
                        "name": "requestor"
                      },
                      "value": {
                        "type": "Identifier",
                        "start": 573,
                        "end": 582,
                        "loc": {
                          "start": {
                            "line": 19,
                            "column": 2
                          },
                          "end": {
                            "line": 19,
                            "column": 11
                          },
                          "identifierName": "requestor"
                        },
                        "name": "requestor"
                      },
                      "extra": {
                        "shorthand": true
                      }
                    },
                    {
                      "type": "ObjectProperty",
                      "start": 586,
                      "end": 594,
                      "loc": {
                        "start": {
                          "line": 20,
                          "column": 2
                        },
                        "end": {
                          "line": 20,
                          "column": 10
                        }
                      },
                      "method": false,
                      "shorthand": true,
                      "computed": false,
                      "key": {
                        "type": "Identifier",
                        "start": 586,
                        "end": 594,
                        "loc": {
                          "start": {
                            "line": 20,
                            "column": 2
                          },
                          "end": {
                            "line": 20,
                            "column": 10
                          },
                          "identifierName": "datetime"
                        },
                        "name": "datetime"
                      },
                      "value": {
                        "type": "Identifier",
                        "start": 586,
                        "end": 594,
                        "loc": {
                          "start": {
                            "line": 20,
                            "column": 2
                          },
                          "end": {
                            "line": 20,
                            "column": 10
                          },
                          "identifierName": "datetime"
                        },
                        "name": "datetime"
                      },
                      "extra": {
                        "shorthand": true
                      }
                    },
                    {
                      "type": "ObjectProperty",
                      "start": 598,
                      "end": 604,
                      "loc": {
                        "start": {
                          "line": 21,
                          "column": 2
                        },
                        "end": {
                          "line": 21,
                          "column": 8
                        }
                      },
                      "method": false,
                      "shorthand": true,
                      "computed": false,
                      "key": {
                        "type": "Identifier",
                        "start": 598,
                        "end": 604,
                        "loc": {
                          "start": {
                            "line": 21,
                            "column": 2
                          },
                          "end": {
                            "line": 21,
                            "column": 8
                          },
                          "identifierName": "status"
                        },
                        "name": "status"
                      },
                      "value": {
                        "type": "Identifier",
                        "start": 598,
                        "end": 604,
                        "loc": {
                          "start": {
                            "line": 21,
                            "column": 2
                          },
                          "end": {
                            "line": 21,
                            "column": 8
                          },
                          "identifierName": "status"
                        },
                        "name": "status"
                      },
                      "extra": {
                        "shorthand": true
                      }
                    }
                  ]
                }
              }
            ],
            "directives": []
          },
          "leadingComments": [],
          "trailingComments": []
        }
      }
    ],
    "directives": []
  },
  "comments": [],
  "tokens": [
    {
      "type": {
        "label": "import",
        "keyword": "import",
        "beforeExpr": false,
        "startsExpr": true,
        "rightAssociative": false,
        "isLoop": false,
        "isAssign": false,
        "prefix": false,
        "postfix": false,
        "binop": null,
        "updateContext": null
      },
      "value": "import",
      "start": 0,
      "end": 6,
      "loc": {
        "start": {
          "line": 1,
          "column": 0
        },
        "end": {
          "line": 1,
          "column": 6
        }
      }
    },
    {
      "type": {
        "label": "name",
        "beforeExpr": false,
        "startsExpr": true,
        "rightAssociative": false,
        "isLoop": false,
        "isAssign": false,
        "prefix": false,
        "postfix": false,
        "binop": null
      },
      "value": "validateLineLength",
      "start": 7,
      "end": 25,
      "loc": {
        "start": {
          "line": 1,
          "column": 7
        },
        "end": {
          "line": 1,
          "column": 25
        }
      }
    },
    {
      "type": {
        "label": "name",
        "beforeExpr": false,
        "startsExpr": true,
        "rightAssociative": false,
        "isLoop": false,
        "isAssign": false,
        "prefix": false,
        "postfix": false,
        "binop": null
      },
      "value": "from",
      "start": 26,
      "end": 30,
      "loc": {
        "start": {
          "line": 1,
          "column": 26
        },
        "end": {
          "line": 1,
          "column": 30
        }
      }
    },
    {
      "type": {
        "label": "string",
        "beforeExpr": false,
        "startsExpr": true,
        "rightAssociative": false,
        "isLoop": false,
        "isAssign": false,
        "prefix": false,
        "postfix": false,
        "binop": null,
        "updateContext": null
      },
      "value": "./validateLineLength.js",
      "start": 31,
      "end": 56,
      "loc": {
        "start": {
          "line": 1,
          "column": 31
        },
        "end": {
          "line": 1,
          "column": 56
        }
      }
    },
    {
      "type": {
        "label": ";",
        "beforeExpr": true,
        "startsExpr": false,
        "rightAssociative": false,
        "isLoop": false,
        "isAssign": false,
        "prefix": false,
        "postfix": false,
        "binop": null,
        "updateContext": null
      },
      "start": 56,
      "end": 57,
      "loc": {
        "start": {
          "line": 1,
          "column": 56
        },
        "end": {
          "line": 1,
          "column": 57
        }
      }
    },
    {
      "type": {
        "label": "import",
        "keyword": "import",
        "beforeExpr": false,
        "startsExpr": true,
        "rightAssociative": false,
        "isLoop": false,
        "isAssign": false,
        "prefix": false,
        "postfix": false,
        "binop": null,
        "updateContext": null
      },
      "value": "import",
      "start": 58,
      "end": 64,
      "loc": {
        "start": {
          "line": 2,
          "column": 0
        },
        "end": {
          "line": 2,
          "column": 6
        }
      }
    },
    {
      "type": {
        "label": "name",
        "beforeExpr": false,
        "startsExpr": true,
        "rightAssociative": false,
        "isLoop": false,
        "isAssign": false,
        "prefix": false,
        "postfix": false,
        "binop": null
      },
      "value": "validateRequiredField",
      "start": 65,
      "end": 86,
      "loc": {
        "start": {
          "line": 2,
          "column": 7
        },
        "end": {
          "line": 2,
          "column": 28
        }
      }
    },
    {
      "type": {
        "label": "name",
        "beforeExpr": false,
        "startsExpr": true,
        "rightAssociative": false,
        "isLoop": false,
        "isAssign": false,
        "prefix": false,
        "postfix": false,
        "binop": null
      },
      "value": "from",
      "start": 87,
      "end": 91,
      "loc": {
        "start": {
          "line": 2,
          "column": 29
        },
        "end": {
          "line": 2,
          "column": 33
        }
      }
    },
    {
      "type": {
        "label": "string",
        "beforeExpr": false,
        "startsExpr": true,
        "rightAssociative": false,
        "isLoop": false,
        "isAssign": false,
        "prefix": false,
        "postfix": false,
        "binop": null,
        "updateContext": null
      },
      "value": "./validateRequiredField.js",
      "start": 92,
      "end": 120,
      "loc": {
        "start": {
          "line": 2,
          "column": 34
        },
        "end": {
          "line": 2,
          "column": 62
        }
      }
    },
    {
      "type": {
        "label": ";",
        "beforeExpr": true,
        "startsExpr": false,
        "rightAssociative": false,
        "isLoop": false,
        "isAssign": false,
        "prefix": false,
        "postfix": false,
        "binop": null,
        "updateContext": null
      },
      "start": 120,
      "end": 121,
      "loc": {
        "start": {
          "line": 2,
          "column": 62
        },
        "end": {
          "line": 2,
          "column": 63
        }
      }
    },
    {
      "type": {
        "label": "import",
        "keyword": "import",
        "beforeExpr": false,
        "startsExpr": true,
        "rightAssociative": false,
        "isLoop": false,
        "isAssign": false,
        "prefix": false,
        "postfix": false,
        "binop": null,
        "updateContext": null
      },
      "value": "import",
      "start": 123,
      "end": 129,
      "loc": {
        "start": {
          "line": 4,
          "column": 0
        },
        "end": {
          "line": 4,
          "column": 6
        }
      }
    },
    {
      "type": {
        "label": "name",
        "beforeExpr": false,
        "startsExpr": true,
        "rightAssociative": false,
        "isLoop": false,
        "isAssign": false,
        "prefix": false,
        "postfix": false,
        "binop": null
      },
      "value": "parseDateTime",
      "start": 130,
      "end": 143,
      "loc": {
        "start": {
          "line": 4,
          "column": 7
        },
        "end": {
          "line": 4,
          "column": 20
        }
      }
    },
    {
      "type": {
        "label": "name",
        "beforeExpr": false,
        "startsExpr": true,
        "rightAssociative": false,
        "isLoop": false,
        "isAssign": false,
        "prefix": false,
        "postfix": false,
        "binop": null
      },
      "value": "from",
      "start": 144,
      "end": 148,
      "loc": {
        "start": {
          "line": 4,
          "column": 21
        },
        "end": {
          "line": 4,
          "column": 25
        }
      }
    },
    {
      "type": {
        "label": "string",
        "beforeExpr": false,
        "startsExpr": true,
        "rightAssociative": false,
        "isLoop": false,
        "isAssign": false,
        "prefix": false,
        "postfix": false,
        "binop": null,
        "updateContext": null
      },
      "value": "./parseDateTime.js",
      "start": 149,
      "end": 169,
      "loc": {
        "start": {
          "line": 4,
          "column": 26
        },
        "end": {
          "line": 4,
          "column": 46
        }
      }
    },
    {
      "type": {
        "label": ";",
        "beforeExpr": true,
        "startsExpr": false,
        "rightAssociative": false,
        "isLoop": false,
        "isAssign": false,
        "prefix": false,
        "postfix": false,
        "binop": null,
        "updateContext": null
      },
      "start": 169,
      "end": 170,
      "loc": {
        "start": {
          "line": 4,
          "column": 46
        },
        "end": {
          "line": 4,
          "column": 47
        }
      }
    },
    {
      "type": {
        "label": "import",
        "keyword": "import",
        "beforeExpr": false,
        "startsExpr": true,
        "rightAssociative": false,
        "isLoop": false,
        "isAssign": false,
        "prefix": false,
        "postfix": false,
        "binop": null,
        "updateContext": null
      },
      "value": "import",
      "start": 171,
      "end": 177,
      "loc": {
        "start": {
          "line": 5,
          "column": 0
        },
        "end": {
          "line": 5,
          "column": 6
        }
      }
    },
    {
      "type": {
        "label": "name",
        "beforeExpr": false,
        "startsExpr": true,
        "rightAssociative": false,
        "isLoop": false,
        "isAssign": false,
        "prefix": false,
        "postfix": false,
        "binop": null
      },
      "value": "parseStatus",
      "start": 178,
      "end": 189,
      "loc": {
        "start": {
          "line": 5,
          "column": 7
        },
        "end": {
          "line": 5,
          "column": 18
        }
      }
    },
    {
      "type": {
        "label": "name",
        "beforeExpr": false,
        "startsExpr": true,
        "rightAssociative": false,
        "isLoop": false,
        "isAssign": false,
        "prefix": false,
        "postfix": false,
        "binop": null
      },
      "value": "from",
      "start": 190,
      "end": 194,
      "loc": {
        "start": {
          "line": 5,
          "column": 19
        },
        "end": {
          "line": 5,
          "column": 23
        }
      }
    },
    {
      "type": {
        "label": "string",
        "beforeExpr": false,
        "startsExpr": true,
        "rightAssociative": false,
        "isLoop": false,
        "isAssign": false,
        "prefix": false,
        "postfix": false,
        "binop": null,
        "updateContext": null
      },
      "value": "./parseStatus.js",
      "start": 195,
      "end": 213,
      "loc": {
        "start": {
          "line": 5,
          "column": 24
        },
        "end": {
          "line": 5,
          "column": 42
        }
      }
    },
    {
      "type": {
        "label": ";",
        "beforeExpr": true,
        "startsExpr": false,
        "rightAssociative": false,
        "isLoop": false,
        "isAssign": false,
        "prefix": false,
        "postfix": false,
        "binop": null,
        "updateContext": null
      },
      "start": 213,
      "end": 214,
      "loc": {
        "start": {
          "line": 5,
          "column": 42
        },
        "end": {
          "line": 5,
          "column": 43
        }
      }
    },
    {
      "type": {
        "label": "export",
        "keyword": "export",
        "beforeExpr": false,
        "startsExpr": false,
        "rightAssociative": false,
        "isLoop": false,
        "isAssign": false,
        "prefix": false,
        "postfix": false,
        "binop": null,
        "updateContext": null
      },
      "value": "export",
      "start": 216,
      "end": 222,
      "loc": {
        "start": {
          "line": 7,
          "column": 0
        },
        "end": {
          "line": 7,
          "column": 6
        }
      }
    },
    {
      "type": {
        "label": "default",
        "keyword": "default",
        "beforeExpr": true,
        "startsExpr": false,
        "rightAssociative": false,
        "isLoop": false,
        "isAssign": false,
        "prefix": false,
        "postfix": false,
        "binop": null,
        "updateContext": null
      },
      "value": "default",
      "start": 223,
      "end": 230,
      "loc": {
        "start": {
          "line": 7,
          "column": 7
        },
        "end": {
          "line": 7,
          "column": 14
        }
      }
    },
    {
      "type": {
        "label": "function",
        "keyword": "function",
        "beforeExpr": false,
        "startsExpr": true,
        "rightAssociative": false,
        "isLoop": false,
        "isAssign": false,
        "prefix": false,
        "postfix": false,
        "binop": null
      },
      "value": "function",
      "start": 231,
      "end": 239,
      "loc": {
        "start": {
          "line": 7,
          "column": 15
        },
        "end": {
          "line": 7,
          "column": 23
        }
      }
    },
    {
      "type": {
        "label": "name",
        "beforeExpr": false,
        "startsExpr": true,
        "rightAssociative": false,
        "isLoop": false,
        "isAssign": false,
        "prefix": false,
        "postfix": false,
        "binop": null
      },
      "value": "parseA4",
      "start": 240,
      "end": 247,
      "loc": {
        "start": {
          "line": 7,
          "column": 24
        },
        "end": {
          "line": 7,
          "column": 31
        }
      }
    },
    {
      "type": {
        "label": "(",
        "beforeExpr": true,
        "startsExpr": true,
        "rightAssociative": false,
        "isLoop": false,
        "isAssign": false,
        "prefix": false,
        "postfix": false,
        "binop": null
      },
      "start": 247,
      "end": 248,
      "loc": {
        "start": {
          "line": 7,
          "column": 31
        },
        "end": {
          "line": 7,
          "column": 32
        }
      }
    },
    {
      "type": {
        "label": "name",
        "beforeExpr": false,
        "startsExpr": true,
        "rightAssociative": false,
        "isLoop": false,
        "isAssign": false,
        "prefix": false,
        "postfix": false,
        "binop": null
      },
      "value": "parts",
      "start": 248,
      "end": 253,
      "loc": {
        "start": {
          "line": 7,
          "column": 32
        },
        "end": {
          "line": 7,
          "column": 37
        }
      }
    },
    {
      "type": {
        "label": ",",
        "beforeExpr": true,
        "startsExpr": false,
        "rightAssociative": false,
        "isLoop": false,
        "isAssign": false,
        "prefix": false,
        "postfix": false,
        "binop": null,
        "updateContext": null
      },
      "start": 253,
      "end": 254,
      "loc": {
        "start": {
          "line": 7,
          "column": 37
        },
        "end": {
          "line": 7,
          "column": 38
        }
      }
    },
    {
      "type": {
        "label": "name",
        "beforeExpr": false,
        "startsExpr": true,
        "rightAssociative": false,
        "isLoop": false,
        "isAssign": false,
        "prefix": false,
        "postfix": false,
        "binop": null
      },
      "value": "options",
      "start": 255,
      "end": 262,
      "loc": {
        "start": {
          "line": 7,
          "column": 39
        },
        "end": {
          "line": 7,
          "column": 46
        }
      }
    },
    {
      "type": {
        "label": ")",
        "beforeExpr": false,
        "startsExpr": false,
        "rightAssociative": false,
        "isLoop": false,
        "isAssign": false,
        "prefix": false,
        "postfix": false,
        "binop": null
      },
      "start": 262,
      "end": 263,
      "loc": {
        "start": {
          "line": 7,
          "column": 46
        },
        "end": {
          "line": 7,
          "column": 47
        }
      }
    },
    {
      "type": {
        "label": "{",
        "beforeExpr": true,
        "startsExpr": true,
        "rightAssociative": false,
        "isLoop": false,
        "isAssign": false,
        "prefix": false,
        "postfix": false,
        "binop": null
      },
      "start": 264,
      "end": 265,
      "loc": {
        "start": {
          "line": 7,
          "column": 48
        },
        "end": {
          "line": 7,
          "column": 49
        }
      }
    },
    {
      "type": {
        "label": "name",
        "beforeExpr": false,
        "startsExpr": true,
        "rightAssociative": false,
        "isLoop": false,
        "isAssign": false,
        "prefix": false,
        "postfix": false,
        "binop": null
      },
      "value": "validateLineLength",
      "start": 267,
      "end": 285,
      "loc": {
        "start": {
          "line": 8,
          "column": 1
        },
        "end": {
          "line": 8,
          "column": 19
        }
      }
    },
    {
      "type": {
        "label": "(",
        "beforeExpr": true,
        "startsExpr": true,
        "rightAssociative": false,
        "isLoop": false,
        "isAssign": false,
        "prefix": false,
        "postfix": false,
        "binop": null
      },
      "start": 285,
      "end": 286,
      "loc": {
        "start": {
          "line": 8,
          "column": 19
        },
        "end": {
          "line": 8,
          "column": 20
        }
      }
    },
    {
      "type": {
        "label": "name",
        "beforeExpr": false,
        "startsExpr": true,
        "rightAssociative": false,
        "isLoop": false,
        "isAssign": false,
        "prefix": false,
        "postfix": false,
        "binop": null
      },
      "value": "parts",
      "start": 286,
      "end": 291,
      "loc": {
        "start": {
          "line": 8,
          "column": 20
        },
        "end": {
          "line": 8,
          "column": 25
        }
      }
    },
    {
      "type": {
        "label": ",",
        "beforeExpr": true,
        "startsExpr": false,
        "rightAssociative": false,
        "isLoop": false,
        "isAssign": false,
        "prefix": false,
        "postfix": false,
        "binop": null,
        "updateContext": null
      },
      "start": 291,
      "end": 292,
      "loc": {
        "start": {
          "line": 8,
          "column": 25
        },
        "end": {
          "line": 8,
          "column": 26
        }
      }
    },
    {
      "type": {
        "label": "string",
        "beforeExpr": false,
        "startsExpr": true,
        "rightAssociative": false,
        "isLoop": false,
        "isAssign": false,
        "prefix": false,
        "postfix": false,
        "binop": null,
        "updateContext": null
      },
      "value": "A4",
      "start": 293,
      "end": 297,
      "loc": {
        "start": {
          "line": 8,
          "column": 27
        },
        "end": {
          "line": 8,
          "column": 31
        }
      }
    },
    {
      "type": {
        "label": ",",
        "beforeExpr": true,
        "startsExpr": false,
        "rightAssociative": false,
        "isLoop": false,
        "isAssign": false,
        "prefix": false,
        "postfix": false,
        "binop": null,
        "updateContext": null
      },
      "start": 297,
      "end": 298,
      "loc": {
        "start": {
          "line": 8,
          "column": 31
        },
        "end": {
          "line": 8,
          "column": 32
        }
      }
    },
    {
      "type": {
        "label": "num",
        "beforeExpr": false,
        "startsExpr": true,
        "rightAssociative": false,
        "isLoop": false,
        "isAssign": false,
        "prefix": false,
        "postfix": false,
        "binop": null,
        "updateContext": null
      },
      "value": 6,
      "start": 299,
      "end": 300,
      "loc": {
        "start": {
          "line": 8,
          "column": 33
        },
        "end": {
          "line": 8,
          "column": 34
        }
      }
    },
    {
      "type": {
        "label": ",",
        "beforeExpr": true,
        "startsExpr": false,
        "rightAssociative": false,
        "isLoop": false,
        "isAssign": false,
        "prefix": false,
        "postfix": false,
        "binop": null,
        "updateContext": null
      },
      "start": 300,
      "end": 301,
      "loc": {
        "start": {
          "line": 8,
          "column": 34
        },
        "end": {
          "line": 8,
          "column": 35
        }
      }
    },
    {
      "type": {
        "label": "name",
        "beforeExpr": false,
        "startsExpr": true,
        "rightAssociative": false,
        "isLoop": false,
        "isAssign": false,
        "prefix": false,
        "postfix": false,
        "binop": null
      },
      "value": "options",
      "start": 302,
      "end": 309,
      "loc": {
        "start": {
          "line": 8,
          "column": 36
        },
        "end": {
          "line": 8,
          "column": 43
        }
      }
    },
    {
      "type": {
        "label": ".",
        "beforeExpr": false,
        "startsExpr": false,
        "rightAssociative": false,
        "isLoop": false,
        "isAssign": false,
        "prefix": false,
        "postfix": false,
        "binop": null,
        "updateContext": null
      },
      "start": 309,
      "end": 310,
      "loc": {
        "start": {
          "line": 8,
          "column": 43
        },
        "end": {
          "line": 8,
          "column": 44
        }
      }
    },
    {
      "type": {
        "label": "name",
        "beforeExpr": false,
        "startsExpr": true,
        "rightAssociative": false,
        "isLoop": false,
        "isAssign": false,
        "prefix": false,
        "postfix": false,
        "binop": null
      },
      "value": "trailing",
      "start": 310,
      "end": 318,
      "loc": {
        "start": {
          "line": 8,
          "column": 44
        },
        "end": {
          "line": 8,
          "column": 52
        }
      }
    },
    {
      "type": {
        "label": ".",
        "beforeExpr": false,
        "startsExpr": false,
        "rightAssociative": false,
        "isLoop": false,
        "isAssign": false,
        "prefix": false,
        "postfix": false,
        "binop": null,
        "updateContext": null
      },
      "start": 318,
      "end": 319,
      "loc": {
        "start": {
          "line": 8,
          "column": 52
        },
        "end": {
          "line": 8,
          "column": 53
        }
      }
    },
    {
      "type": {
        "label": "name",
        "beforeExpr": false,
        "startsExpr": true,
        "rightAssociative": false,
        "isLoop": false,
        "isAssign": false,
        "prefix": false,
        "postfix": false,
        "binop": null
      },
      "value": "A4",
      "start": 319,
      "end": 321,
      "loc": {
        "start": {
          "line": 8,
          "column": 53
        },
        "end": {
          "line": 8,
          "column": 55
        }
      }
    },
    {
      "type": {
        "label": ")",
        "beforeExpr": false,
        "startsExpr": false,
        "rightAssociative": false,
        "isLoop": false,
        "isAssign": false,
        "prefix": false,
        "postfix": false,
        "binop": null
      },
      "start": 321,
      "end": 322,
      "loc": {
        "start": {
          "line": 8,
          "column": 55
        },
        "end": {
          "line": 8,
          "column": 56
        }
      }
    },
    {
      "type": {
        "label": ";",
        "beforeExpr": true,
        "startsExpr": false,
        "rightAssociative": false,
        "isLoop": false,
        "isAssign": false,
        "prefix": false,
        "postfix": false,
        "binop": null,
        "updateContext": null
      },
      "start": 322,
      "end": 323,
      "loc": {
        "start": {
          "line": 8,
          "column": 56
        },
        "end": {
          "line": 8,
          "column": 57
        }
      }
    },
    {
      "type": {
        "label": "name",
        "beforeExpr": false,
        "startsExpr": true,
        "rightAssociative": false,
        "isLoop": false,
        "isAssign": false,
        "prefix": false,
        "postfix": false,
        "binop": null
      },
      "value": "validateRequiredField",
      "start": 325,
      "end": 346,
      "loc": {
        "start": {
          "line": 9,
          "column": 1
        },
        "end": {
          "line": 9,
          "column": 22
        }
      }
    },
    {
      "type": {
        "label": "(",
        "beforeExpr": true,
        "startsExpr": true,
        "rightAssociative": false,
        "isLoop": false,
        "isAssign": false,
        "prefix": false,
        "postfix": false,
        "binop": null
      },
      "start": 346,
      "end": 347,
      "loc": {
        "start": {
          "line": 9,
          "column": 22
        },
        "end": {
          "line": 9,
          "column": 23
        }
      }
    },
    {
      "type": {
        "label": "name",
        "beforeExpr": false,
        "startsExpr": true,
        "rightAssociative": false,
        "isLoop": false,
        "isAssign": false,
        "prefix": false,
        "postfix": false,
        "binop": null
      },
      "value": "parts",
      "start": 347,
      "end": 352,
      "loc": {
        "start": {
          "line": 9,
          "column": 23
        },
        "end": {
          "line": 9,
          "column": 28
        }
      }
    },
    {
      "type": {
        "label": ",",
        "beforeExpr": true,
        "startsExpr": false,
        "rightAssociative": false,
        "isLoop": false,
        "isAssign": false,
        "prefix": false,
        "postfix": false,
        "binop": null,
        "updateContext": null
      },
      "start": 352,
      "end": 353,
      "loc": {
        "start": {
          "line": 9,
          "column": 28
        },
        "end": {
          "line": 9,
          "column": 29
        }
      }
    },
    {
      "type": {
        "label": "string",
        "beforeExpr": false,
        "startsExpr": true,
        "rightAssociative": false,
        "isLoop": false,
        "isAssign": false,
        "prefix": false,
        "postfix": false,
        "binop": null,
        "updateContext": null
      },
      "value": "date",
      "start": 354,
      "end": 360,
      "loc": {
        "start": {
          "line": 9,
          "column": 30
        },
        "end": {
          "line": 9,
          "column": 36
        }
      }
    },
    {
      "type": {
        "label": ",",
        "beforeExpr": true,
        "startsExpr": false,
        "rightAssociative": false,
        "isLoop": false,
        "isAssign": false,
        "prefix": false,
        "postfix": false,
        "binop": null,
        "updateContext": null
      },
      "start": 360,
      "end": 361,
      "loc": {
        "start": {
          "line": 9,
          "column": 36
        },
        "end": {
          "line": 9,
          "column": 37
        }
      }
    },
    {
      "type": {
        "label": "num",
        "beforeExpr": false,
        "startsExpr": true,
        "rightAssociative": false,
        "isLoop": false,
        "isAssign": false,
        "prefix": false,
        "postfix": false,
        "binop": null,
        "updateContext": null
      },
      "value": 4,
      "start": 362,
      "end": 363,
      "loc": {
        "start": {
          "line": 9,
          "column": 38
        },
        "end": {
          "line": 9,
          "column": 39
        }
      }
    },
    {
      "type": {
        "label": ")",
        "beforeExpr": false,
        "startsExpr": false,
        "rightAssociative": false,
        "isLoop": false,
        "isAssign": false,
        "prefix": false,
        "postfix": false,
        "binop": null
      },
      "start": 363,
      "end": 364,
      "loc": {
        "start": {
          "line": 9,
          "column": 39
        },
        "end": {
          "line": 9,
          "column": 40
        }
      }
    },
    {
      "type": {
        "label": ";",
        "beforeExpr": true,
        "startsExpr": false,
        "rightAssociative": false,
        "isLoop": false,
        "isAssign": false,
        "prefix": false,
        "postfix": false,
        "binop": null,
        "updateContext": null
      },
      "start": 364,
      "end": 365,
      "loc": {
        "start": {
          "line": 9,
          "column": 40
        },
        "end": {
          "line": 9,
          "column": 41
        }
      }
    },
    {
      "type": {
        "label": "const",
        "keyword": "const",
        "beforeExpr": false,
        "startsExpr": false,
        "rightAssociative": false,
        "isLoop": false,
        "isAssign": false,
        "prefix": false,
        "postfix": false,
        "binop": null,
        "updateContext": null
      },
      "value": "const",
      "start": 368,
      "end": 373,
      "loc": {
        "start": {
          "line": 11,
          "column": 1
        },
        "end": {
          "line": 11,
          "column": 6
        }
      }
    },
    {
      "type": {
        "label": "[",
        "beforeExpr": true,
        "startsExpr": true,
        "rightAssociative": false,
        "isLoop": false,
        "isAssign": false,
        "prefix": false,
        "postfix": false,
        "binop": null,
        "updateContext": null
      },
      "start": 374,
      "end": 375,
      "loc": {
        "start": {
          "line": 11,
          "column": 7
        },
        "end": {
          "line": 11,
          "column": 8
        }
      }
    },
    {
      "type": {
        "label": "name",
        "beforeExpr": false,
        "startsExpr": true,
        "rightAssociative": false,
        "isLoop": false,
        "isAssign": false,
        "prefix": false,
        "postfix": false,
        "binop": null
      },
      "value": "descriptor",
      "start": 375,
      "end": 385,
      "loc": {
        "start": {
          "line": 11,
          "column": 8
        },
        "end": {
          "line": 11,
          "column": 18
        }
      }
    },
    {
      "type": {
        "label": ",",
        "beforeExpr": true,
        "startsExpr": false,
        "rightAssociative": false,
        "isLoop": false,
        "isAssign": false,
        "prefix": false,
        "postfix": false,
        "binop": null,
        "updateContext": null
      },
      "start": 385,
      "end": 386,
      "loc": {
        "start": {
          "line": 11,
          "column": 18
        },
        "end": {
          "line": 11,
          "column": 19
        }
      }
    },
    {
      "type": {
        "label": "name",
        "beforeExpr": false,
        "startsExpr": true,
        "rightAssociative": false,
        "isLoop": false,
        "isAssign": false,
        "prefix": false,
        "postfix": false,
        "binop": null
      },
      "value": "reference",
      "start": 387,
      "end": 396,
      "loc": {
        "start": {
          "line": 11,
          "column": 20
        },
        "end": {
          "line": 11,
          "column": 29
        }
      }
    },
    {
      "type": {
        "label": ",",
        "beforeExpr": true,
        "startsExpr": false,
        "rightAssociative": false,
        "isLoop": false,
        "isAssign": false,
        "prefix": false,
        "postfix": false,
        "binop": null,
        "updateContext": null
      },
      "start": 396,
      "end": 397,
      "loc": {
        "start": {
          "line": 11,
          "column": 29
        },
        "end": {
          "line": 11,
          "column": 30
        }
      }
    },
    {
      "type": {
        "label": "name",
        "beforeExpr": false,
        "startsExpr": true,
        "rightAssociative": false,
        "isLoop": false,
        "isAssign": false,
        "prefix": false,
        "postfix": false,
        "binop": null
      },
      "value": "requestor",
      "start": 398,
      "end": 407,
      "loc": {
        "start": {
          "line": 11,
          "column": 31
        },
        "end": {
          "line": 11,
          "column": 40
        }
      }
    },
    {
      "type": {
        "label": ",",
        "beforeExpr": true,
        "startsExpr": false,
        "rightAssociative": false,
        "isLoop": false,
        "isAssign": false,
        "prefix": false,
        "postfix": false,
        "binop": null,
        "updateContext": null
      },
      "start": 407,
      "end": 408,
      "loc": {
        "start": {
          "line": 11,
          "column": 40
        },
        "end": {
          "line": 11,
          "column": 41
        }
      }
    },
    {
      "type": {
        "label": "name",
        "beforeExpr": false,
        "startsExpr": true,
        "rightAssociative": false,
        "isLoop": false,
        "isAssign": false,
        "prefix": false,
        "postfix": false,
        "binop": null
      },
      "value": "date",
      "start": 409,
      "end": 413,
      "loc": {
        "start": {
          "line": 11,
          "column": 42
        },
        "end": {
          "line": 11,
          "column": 46
        }
      }
    },
    {
      "type": {
        "label": ",",
        "beforeExpr": true,
        "startsExpr": false,
        "rightAssociative": false,
        "isLoop": false,
        "isAssign": false,
        "prefix": false,
        "postfix": false,
        "binop": null,
        "updateContext": null
      },
      "start": 413,
      "end": 414,
      "loc": {
        "start": {
          "line": 11,
          "column": 46
        },
        "end": {
          "line": 11,
          "column": 47
        }
      }
    },
    {
      "type": {
        "label": "name",
        "beforeExpr": false,
        "startsExpr": true,
        "rightAssociative": false,
        "isLoop": false,
        "isAssign": false,
        "prefix": false,
        "postfix": false,
        "binop": null
      },
      "value": "time",
      "start": 415,
      "end": 419,
      "loc": {
        "start": {
          "line": 11,
          "column": 48
        },
        "end": {
          "line": 11,
          "column": 52
        }
      }
    },
    {
      "type": {
        "label": ",",
        "beforeExpr": true,
        "startsExpr": false,
        "rightAssociative": false,
        "isLoop": false,
        "isAssign": false,
        "prefix": false,
        "postfix": false,
        "binop": null,
        "updateContext": null
      },
      "start": 419,
      "end": 420,
      "loc": {
        "start": {
          "line": 11,
          "column": 52
        },
        "end": {
          "line": 11,
          "column": 53
        }
      }
    },
    {
      "type": {
        "label": "name",
        "beforeExpr": false,
        "startsExpr": true,
        "rightAssociative": false,
        "isLoop": false,
        "isAssign": false,
        "prefix": false,
        "postfix": false,
        "binop": null
      },
      "value": "statusString",
      "start": 421,
      "end": 433,
      "loc": {
        "start": {
          "line": 11,
          "column": 54
        },
        "end": {
          "line": 11,
          "column": 66
        }
      }
    },
    {
      "type": {
        "label": "]",
        "beforeExpr": false,
        "startsExpr": false,
        "rightAssociative": false,
        "isLoop": false,
        "isAssign": false,
        "prefix": false,
        "postfix": false,
        "binop": null,
        "updateContext": null
      },
      "start": 433,
      "end": 434,
      "loc": {
        "start": {
          "line": 11,
          "column": 66
        },
        "end": {
          "line": 11,
          "column": 67
        }
      }
    },
    {
      "type": {
        "label": "=",
        "beforeExpr": true,
        "startsExpr": false,
        "rightAssociative": false,
        "isLoop": false,
        "isAssign": true,
        "prefix": false,
        "postfix": false,
        "binop": null,
        "updateContext": null
      },
      "value": "=",
      "start": 435,
      "end": 436,
      "loc": {
        "start": {
          "line": 11,
          "column": 68
        },
        "end": {
          "line": 11,
          "column": 69
        }
      }
    },
    {
      "type": {
        "label": "name",
        "beforeExpr": false,
        "startsExpr": true,
        "rightAssociative": false,
        "isLoop": false,
        "isAssign": false,
        "prefix": false,
        "postfix": false,
        "binop": null
      },
      "value": "parts",
      "start": 437,
      "end": 442,
      "loc": {
        "start": {
          "line": 11,
          "column": 70
        },
        "end": {
          "line": 11,
          "column": 75
        }
      }
    },
    {
      "type": {
        "label": ";",
        "beforeExpr": true,
        "startsExpr": false,
        "rightAssociative": false,
        "isLoop": false,
        "isAssign": false,
        "prefix": false,
        "postfix": false,
        "binop": null,
        "updateContext": null
      },
      "start": 442,
      "end": 443,
      "loc": {
        "start": {
          "line": 11,
          "column": 75
        },
        "end": {
          "line": 11,
          "column": 76
        }
      }
    },
    {
      "type": {
        "label": "const",
        "keyword": "const",
        "beforeExpr": false,
        "startsExpr": false,
        "rightAssociative": false,
        "isLoop": false,
        "isAssign": false,
        "prefix": false,
        "postfix": false,
        "binop": null,
        "updateContext": null
      },
      "value": "const",
      "start": 446,
      "end": 451,
      "loc": {
        "start": {
          "line": 13,
          "column": 1
        },
        "end": {
          "line": 13,
          "column": 6
        }
      }
    },
    {
      "type": {
        "label": "name",
        "beforeExpr": false,
        "startsExpr": true,
        "rightAssociative": false,
        "isLoop": false,
        "isAssign": false,
        "prefix": false,
        "postfix": false,
        "binop": null
      },
      "value": "datetime",
      "start": 452,
      "end": 460,
      "loc": {
        "start": {
          "line": 13,
          "column": 7
        },
        "end": {
          "line": 13,
          "column": 15
        }
      }
    },
    {
      "type": {
        "label": "=",
        "beforeExpr": true,
        "startsExpr": false,
        "rightAssociative": false,
        "isLoop": false,
        "isAssign": true,
        "prefix": false,
        "postfix": false,
        "binop": null,
        "updateContext": null
      },
      "value": "=",
      "start": 461,
      "end": 462,
      "loc": {
        "start": {
          "line": 13,
          "column": 16
        },
        "end": {
          "line": 13,
          "column": 17
        }
      }
    },
    {
      "type": {
        "label": "name",
        "beforeExpr": false,
        "startsExpr": true,
        "rightAssociative": false,
        "isLoop": false,
        "isAssign": false,
        "prefix": false,
        "postfix": false,
        "binop": null
      },
      "value": "parseDateTime",
      "start": 463,
      "end": 476,
      "loc": {
        "start": {
          "line": 13,
          "column": 18
        },
        "end": {
          "line": 13,
          "column": 31
        }
      }
    },
    {
      "type": {
        "label": "(",
        "beforeExpr": true,
        "startsExpr": true,
        "rightAssociative": false,
        "isLoop": false,
        "isAssign": false,
        "prefix": false,
        "postfix": false,
        "binop": null
      },
      "start": 476,
      "end": 477,
      "loc": {
        "start": {
          "line": 13,
          "column": 31
        },
        "end": {
          "line": 13,
          "column": 32
        }
      }
    },
    {
      "type": {
        "label": "name",
        "beforeExpr": false,
        "startsExpr": true,
        "rightAssociative": false,
        "isLoop": false,
        "isAssign": false,
        "prefix": false,
        "postfix": false,
        "binop": null
      },
      "value": "date",
      "start": 477,
      "end": 481,
      "loc": {
        "start": {
          "line": 13,
          "column": 32
        },
        "end": {
          "line": 13,
          "column": 36
        }
      }
    },
    {
      "type": {
        "label": ",",
        "beforeExpr": true,
        "startsExpr": false,
        "rightAssociative": false,
        "isLoop": false,
        "isAssign": false,
        "prefix": false,
        "postfix": false,
        "binop": null,
        "updateContext": null
      },
      "start": 481,
      "end": 482,
      "loc": {
        "start": {
          "line": 13,
          "column": 36
        },
        "end": {
          "line": 13,
          "column": 37
        }
      }
    },
    {
      "type": {
        "label": "name",
        "beforeExpr": false,
        "startsExpr": true,
        "rightAssociative": false,
        "isLoop": false,
        "isAssign": false,
        "prefix": false,
        "postfix": false,
        "binop": null
      },
      "value": "time",
      "start": 483,
      "end": 487,
      "loc": {
        "start": {
          "line": 13,
          "column": 38
        },
        "end": {
          "line": 13,
          "column": 42
        }
      }
    },
    {
      "type": {
        "label": ")",
        "beforeExpr": false,
        "startsExpr": false,
        "rightAssociative": false,
        "isLoop": false,
        "isAssign": false,
        "prefix": false,
        "postfix": false,
        "binop": null
      },
      "start": 487,
      "end": 488,
      "loc": {
        "start": {
          "line": 13,
          "column": 42
        },
        "end": {
          "line": 13,
          "column": 43
        }
      }
    },
    {
      "type": {
        "label": ";",
        "beforeExpr": true,
        "startsExpr": false,
        "rightAssociative": false,
        "isLoop": false,
        "isAssign": false,
        "prefix": false,
        "postfix": false,
        "binop": null,
        "updateContext": null
      },
      "start": 488,
      "end": 489,
      "loc": {
        "start": {
          "line": 13,
          "column": 43
        },
        "end": {
          "line": 13,
          "column": 44
        }
      }
    },
    {
      "type": {
        "label": "const",
        "keyword": "const",
        "beforeExpr": false,
        "startsExpr": false,
        "rightAssociative": false,
        "isLoop": false,
        "isAssign": false,
        "prefix": false,
        "postfix": false,
        "binop": null,
        "updateContext": null
      },
      "value": "const",
      "start": 491,
      "end": 496,
      "loc": {
        "start": {
          "line": 14,
          "column": 1
        },
        "end": {
          "line": 14,
          "column": 6
        }
      }
    },
    {
      "type": {
        "label": "name",
        "beforeExpr": false,
        "startsExpr": true,
        "rightAssociative": false,
        "isLoop": false,
        "isAssign": false,
        "prefix": false,
        "postfix": false,
        "binop": null
      },
      "value": "status",
      "start": 497,
      "end": 503,
      "loc": {
        "start": {
          "line": 14,
          "column": 7
        },
        "end": {
          "line": 14,
          "column": 13
        }
      }
    },
    {
      "type": {
        "label": "=",
        "beforeExpr": true,
        "startsExpr": false,
        "rightAssociative": false,
        "isLoop": false,
        "isAssign": true,
        "prefix": false,
        "postfix": false,
        "binop": null,
        "updateContext": null
      },
      "value": "=",
      "start": 504,
      "end": 505,
      "loc": {
        "start": {
          "line": 14,
          "column": 14
        },
        "end": {
          "line": 14,
          "column": 15
        }
      }
    },
    {
      "type": {
        "label": "name",
        "beforeExpr": false,
        "startsExpr": true,
        "rightAssociative": false,
        "isLoop": false,
        "isAssign": false,
        "prefix": false,
        "postfix": false,
        "binop": null
      },
      "value": "parseStatus",
      "start": 506,
      "end": 517,
      "loc": {
        "start": {
          "line": 14,
          "column": 16
        },
        "end": {
          "line": 14,
          "column": 27
        }
      }
    },
    {
      "type": {
        "label": "(",
        "beforeExpr": true,
        "startsExpr": true,
        "rightAssociative": false,
        "isLoop": false,
        "isAssign": false,
        "prefix": false,
        "postfix": false,
        "binop": null
      },
      "start": 517,
      "end": 518,
      "loc": {
        "start": {
          "line": 14,
          "column": 27
        },
        "end": {
          "line": 14,
          "column": 28
        }
      }
    },
    {
      "type": {
        "label": "name",
        "beforeExpr": false,
        "startsExpr": true,
        "rightAssociative": false,
        "isLoop": false,
        "isAssign": false,
        "prefix": false,
        "postfix": false,
        "binop": null
      },
      "value": "statusString",
      "start": 518,
      "end": 530,
      "loc": {
        "start": {
          "line": 14,
          "column": 28
        },
        "end": {
          "line": 14,
          "column": 40
        }
      }
    },
    {
      "type": {
        "label": ")",
        "beforeExpr": false,
        "startsExpr": false,
        "rightAssociative": false,
        "isLoop": false,
        "isAssign": false,
        "prefix": false,
        "postfix": false,
        "binop": null
      },
      "start": 530,
      "end": 531,
      "loc": {
        "start": {
          "line": 14,
          "column": 40
        },
        "end": {
          "line": 14,
          "column": 41
        }
      }
    },
    {
      "type": {
        "label": ";",
        "beforeExpr": true,
        "startsExpr": false,
        "rightAssociative": false,
        "isLoop": false,
        "isAssign": false,
        "prefix": false,
        "postfix": false,
        "binop": null,
        "updateContext": null
      },
      "start": 531,
      "end": 532,
      "loc": {
        "start": {
          "line": 14,
          "column": 41
        },
        "end": {
          "line": 14,
          "column": 42
        }
      }
    },
    {
      "type": {
        "label": "return",
        "keyword": "return",
        "beforeExpr": true,
        "startsExpr": false,
        "rightAssociative": false,
        "isLoop": false,
        "isAssign": false,
        "prefix": false,
        "postfix": false,
        "binop": null,
        "updateContext": null
      },
      "value": "return",
      "start": 535,
      "end": 541,
      "loc": {
        "start": {
          "line": 16,
          "column": 1
        },
        "end": {
          "line": 16,
          "column": 7
        }
      }
    },
    {
      "type": {
        "label": "{",
        "beforeExpr": true,
        "startsExpr": true,
        "rightAssociative": false,
        "isLoop": false,
        "isAssign": false,
        "prefix": false,
        "postfix": false,
        "binop": null
      },
      "start": 542,
      "end": 543,
      "loc": {
        "start": {
          "line": 16,
          "column": 8
        },
        "end": {
          "line": 16,
          "column": 9
        }
      }
    },
    {
      "type": {
        "label": "name",
        "beforeExpr": false,
        "startsExpr": true,
        "rightAssociative": false,
        "isLoop": false,
        "isAssign": false,
        "prefix": false,
        "postfix": false,
        "binop": null
      },
      "value": "descriptor",
      "start": 546,
      "end": 556,
      "loc": {
        "start": {
          "line": 17,
          "column": 2
        },
        "end": {
          "line": 17,
          "column": 12
        }
      }
    },
    {
      "type": {
        "label": ",",
        "beforeExpr": true,
        "startsExpr": false,
        "rightAssociative": false,
        "isLoop": false,
        "isAssign": false,
        "prefix": false,
        "postfix": false,
        "binop": null,
        "updateContext": null
      },
      "start": 556,
      "end": 557,
      "loc": {
        "start": {
          "line": 17,
          "column": 12
        },
        "end": {
          "line": 17,
          "column": 13
        }
      }
    },
    {
      "type": {
        "label": "name",
        "beforeExpr": false,
        "startsExpr": true,
        "rightAssociative": false,
        "isLoop": false,
        "isAssign": false,
        "prefix": false,
        "postfix": false,
        "binop": null
      },
      "value": "reference",
      "start": 560,
      "end": 569,
      "loc": {
        "start": {
          "line": 18,
          "column": 2
        },
        "end": {
          "line": 18,
          "column": 11
        }
      }
    },
    {
      "type": {
        "label": ",",
        "beforeExpr": true,
        "startsExpr": false,
        "rightAssociative": false,
        "isLoop": false,
        "isAssign": false,
        "prefix": false,
        "postfix": false,
        "binop": null,
        "updateContext": null
      },
      "start": 569,
      "end": 570,
      "loc": {
        "start": {
          "line": 18,
          "column": 11
        },
        "end": {
          "line": 18,
          "column": 12
        }
      }
    },
    {
      "type": {
        "label": "name",
        "beforeExpr": false,
        "startsExpr": true,
        "rightAssociative": false,
        "isLoop": false,
        "isAssign": false,
        "prefix": false,
        "postfix": false,
        "binop": null
      },
      "value": "requestor",
      "start": 573,
      "end": 582,
      "loc": {
        "start": {
          "line": 19,
          "column": 2
        },
        "end": {
          "line": 19,
          "column": 11
        }
      }
    },
    {
      "type": {
        "label": ",",
        "beforeExpr": true,
        "startsExpr": false,
        "rightAssociative": false,
        "isLoop": false,
        "isAssign": false,
        "prefix": false,
        "postfix": false,
        "binop": null,
        "updateContext": null
      },
      "start": 582,
      "end": 583,
      "loc": {
        "start": {
          "line": 19,
          "column": 11
        },
        "end": {
          "line": 19,
          "column": 12
        }
      }
    },
    {
      "type": {
        "label": "name",
        "beforeExpr": false,
        "startsExpr": true,
        "rightAssociative": false,
        "isLoop": false,
        "isAssign": false,
        "prefix": false,
        "postfix": false,
        "binop": null
      },
      "value": "datetime",
      "start": 586,
      "end": 594,
      "loc": {
        "start": {
          "line": 20,
          "column": 2
        },
        "end": {
          "line": 20,
          "column": 10
        }
      }
    },
    {
      "type": {
        "label": ",",
        "beforeExpr": true,
        "startsExpr": false,
        "rightAssociative": false,
        "isLoop": false,
        "isAssign": false,
        "prefix": false,
        "postfix": false,
        "binop": null,
        "updateContext": null
      },
      "start": 594,
      "end": 595,
      "loc": {
        "start": {
          "line": 20,
          "column": 10
        },
        "end": {
          "line": 20,
          "column": 11
        }
      }
    },
    {
      "type": {
        "label": "name",
        "beforeExpr": false,
        "startsExpr": true,
        "rightAssociative": false,
        "isLoop": false,
        "isAssign": false,
        "prefix": false,
        "postfix": false,
        "binop": null
      },
      "value": "status",
      "start": 598,
      "end": 604,
      "loc": {
        "start": {
          "line": 21,
          "column": 2
        },
        "end": {
          "line": 21,
          "column": 8
        }
      }
    },
    {
      "type": {
        "label": ",",
        "beforeExpr": true,
        "startsExpr": false,
        "rightAssociative": false,
        "isLoop": false,
        "isAssign": false,
        "prefix": false,
        "postfix": false,
        "binop": null,
        "updateContext": null
      },
      "start": 604,
      "end": 605,
      "loc": {
        "start": {
          "line": 21,
          "column": 8
        },
        "end": {
          "line": 21,
          "column": 9
        }
      }
    },
    {
      "type": {
        "label": "}",
        "beforeExpr": false,
        "startsExpr": false,
        "rightAssociative": false,
        "isLoop": false,
        "isAssign": false,
        "prefix": false,
        "postfix": false,
        "binop": null
      },
      "start": 607,
      "end": 608,
      "loc": {
        "start": {
          "line": 22,
          "column": 1
        },
        "end": {
          "line": 22,
          "column": 2
        }
      }
    },
    {
      "type": {
        "label": ";",
        "beforeExpr": true,
        "startsExpr": false,
        "rightAssociative": false,
        "isLoop": false,
        "isAssign": false,
        "prefix": false,
        "postfix": false,
        "binop": null,
        "updateContext": null
      },
      "start": 608,
      "end": 609,
      "loc": {
        "start": {
          "line": 22,
          "column": 2
        },
        "end": {
          "line": 22,
          "column": 3
        }
      }
    },
    {
      "type": {
        "label": "}",
        "beforeExpr": false,
        "startsExpr": false,
        "rightAssociative": false,
        "isLoop": false,
        "isAssign": false,
        "prefix": false,
        "postfix": false,
        "binop": null
      },
      "start": 610,
      "end": 611,
      "loc": {
        "start": {
          "line": 23,
          "column": 0
        },
        "end": {
          "line": 23,
          "column": 1
        }
      }
    },
    {
      "type": {
        "label": "eof",
        "beforeExpr": false,
        "startsExpr": false,
        "rightAssociative": false,
        "isLoop": false,
        "isAssign": false,
        "prefix": false,
        "postfix": false,
        "binop": null,
        "updateContext": null
      },
      "start": 612,
      "end": 612,
      "loc": {
        "start": {
          "line": 24,
          "column": 0
        },
        "end": {
          "line": 24,
          "column": 0
        }
      }
    }
  ]
}